ArmoryApi/__init__.py
ArmoryApi/armoryAPI.py
ArmoryApi/armoryAPIUser.py
armory_api_lib-1.1.dist-info/LICENCE
armory_api_lib-1.1.dist-info/METADATA
armory_api_lib-1.1.dist-info/WHEEL
armory_api_lib-1.1.dist-info/top_level.txt
armory_api_lib-1.1.dist-info/RECORD
