Metadata-Version: 2.1
Name: armory-api-lib
Version: 1.1
Summary: A Armory API Package
Author-email: Rl242Dev <robin.lachand@gmail.com>
Project-URL: Homepage, https://github.com/Rl242Dev/ArmoryTools
Project-URL: documentation, https://github.com/Rl242Dev/ArmoryTools#readme
Classifier: Programming Language :: Python :: 3
Classifier: License :: OSI Approved :: MIT License
Classifier: Operating System :: OS Independent
Requires-Python: >=3.7
License-File: LICENCE
Requires-Dist: requests
